<?xml version="1.0" encoding="UTF-8"?>
<objects serializationModel="Studio.02.00.00">
	<object class="AudioFile" id="{a131669c-2323-4eaf-85bd-dd091317c061}">
		<property name="assetPath">
			<value>SankFX_Metal_Fail.wav</value>
		</property>
		<property name="frequencyInKHz">
			<value>48</value>
		</property>
		<property name="channelCount">
			<value>1</value>
		</property>
		<property name="length">
			<value>2.8536874999999999</value>
		</property>
		<relationship name="masterAssetFolder">
			<destination>{8de2ebae-931c-46cf-b97d-0ba3557f3586}</destination>
		</relationship>
	</object>
</objects>
